myfunctions_viksan17/__init__.py
myfunctions_viksan17/math.py
myfunctions_viksan17-0.0.7.dist-info/METADATA
myfunctions_viksan17-0.0.7.dist-info/WHEEL
myfunctions_viksan17-0.0.7.dist-info/top_level.txt
myfunctions_viksan17-0.0.7.dist-info/RECORD
