Metadata-Version: 2.1
Name: myfunctions-viksan17
Version: 0.0.7
Summary: A description of your package
Home-page: https://github.com/viksan17/
Author: Victor Sanabria
Author-email: vicsanab92@gmail.com
License: MIT
Platform: UNKNOWN
Classifier: Programming Language :: Python :: 3
Classifier: License :: OSI Approved :: MIT License
Classifier: Operating System :: OS Independent
Requires-Python: >=3.6
